.gitignore
LICENSE
MANIFEST.in
README.rst
requirements-dev.in
requirements.in
requirements2.txt
requirements3.txt
setup.py
tox.ini
.circleci/config.yml
girder_jupyter/__init__.py
girder_jupyter.egg-info/PKG-INFO
girder_jupyter.egg-info/SOURCES.txt
girder_jupyter.egg-info/dependency_links.txt
girder_jupyter.egg-info/requires.txt
girder_jupyter.egg-info/top_level.txt
girder_jupyter/contents/__init__.py
girder_jupyter/contents/girderfilemanager.py
tests/__init__.py
tests/constants.py
tests/test_girder_contents_api.py
tests/ansible/ansible.cfg
tests/ansible/setup.yml