Metadata-Version: 1.1
Name: girder-jupyter
Version: 0.1.0
Summary: A jupyter content manager for Girder
Home-page: https://github.com/girder/girder_jupyter
Author: Kitware Inc
Author-email: kitware@kitware.com
License: BSD 3-Clause
Keywords: jupyter girder data management
Platform: UNKNOWN
Classifier: Development Status :: 4 - Beta
Classifier: Framework :: Jupyter
Classifier: License :: OSI Approved :: BSD License
Classifier: Programming Language :: Python :: 2.7
Classifier: Programming Language :: Python :: 3.6
